coolpi/__init__.py
coolpi/auxiliary/common_operations.py
coolpi/auxiliary/errors.py
coolpi/auxiliary/export_data.py
coolpi/auxiliary/load_data.py
coolpi/auxiliary/plot.py
coolpi/colour/cat_models.py
coolpi/colour/cct_operations.py
coolpi/colour/cie_colour_spectral.py
coolpi/colour/colour_difference.py
coolpi/colour/colour_space_conversion.py
coolpi/colour/lambda_operations.py
coolpi/data/__init__.py
coolpi/data/cie/__init__.py
coolpi/data/cie/cie_cfb.json
coolpi/data/cie/cie_cmf.json
coolpi/data/cie/cie_rgbcmf.json
coolpi/data/cie/cie_s_ctt.json
coolpi/data/cie/cie_spd.json
coolpi/data/cie/cie_white_point.json
coolpi/data/colourchecker/__init__.py
coolpi/data/colourchecker/XYZ/__init__.py
coolpi/data/colourchecker/XYZ/colour_checker_xyz_data.json
coolpi/data/colourchecker/coordinates/__init__.py
coolpi/data/colourchecker/coordinates/patches_coordinates.json
coolpi/data/colourchecker/img/CCC.jpg
coolpi/data/colourchecker/img/CCDSG.jpg
coolpi/data/colourchecker/img/CCPP2.jpg
coolpi/data/colourchecker/img/CCPPV.jpg
coolpi/data/colourchecker/img/SCK100.jpg
coolpi/data/colourchecker/img/XRCCPP.jpg
coolpi/data/colourchecker/img/__init__.py
coolpi/data/colourchecker/reflectance/__init__.py
coolpi/data/colourchecker/reflectance/colour_checker_reflectance_data.json
coolpi/gui/app.py
coolpi/gui/config.py
coolpi/gui/controller.py
coolpi/gui/gui.py
coolpi/gui/model.py
coolpi/gui/assets/config/config.json
coolpi/gui/assets/icon/cci.png
coolpi/gui/assets/icon/cde.png
coolpi/gui/assets/icon/cpt.png
coolpi/gui/assets/icon/csc.png
coolpi/gui/assets/icon/quit.png
coolpi/gui/assets/icon/rcip.png
coolpi/gui/assets/icon/save.png
coolpi/gui/assets/icon/spc.png
coolpi/gui/assets/icon/spd.png
coolpi/gui/assets/icon/zoom.png
coolpi/gui/assets/logo/LBI.png
coolpi/gui/assets/logo/coolpi.png
coolpi/gui/assets/logo/indigo.png
coolpi/gui/assets/temp/default.jpg
coolpi/image/colourchecker.py
coolpi/image/colourchecker_detection.py
coolpi/image/image_objects.py
coolpi/image/patch_extraction.py
coolpi-0.1.19.dist-info/LICENSE.txt
coolpi-0.1.19.dist-info/METADATA
coolpi-0.1.19.dist-info/WHEEL
coolpi-0.1.19.dist-info/top_level.txt
coolpi-0.1.19.dist-info/RECORD
