Metadata-Version: 2.1
Name: coolpi
Version: 0.1.19
Summary: COlour Operations Library for Processing Images
Author-email: Adolfo Molada Tebar <a.molada.tebar@gmail.com>
Project-URL: COOLPI Documentation, https://graffitiprojectindigo.github.io/coolpi/
Project-URL: COOLPI Source, https://github.com/GraffitiProjectINDIGO/coolpi/tree/main/src/coolpi
Project-URL: COOLPI Tests, https://github.com/GraffitiProjectINDIGO/coolpi/tree/main/tests
Project-URL: GitHub, https://github.com/GraffitiProjectINDIGO/coolpi
Project-URL: GitHub Notebooks, https://github.com/GraffitiProjectINDIGO/coolpi/tree/main/notebooks
Project-URL: INDIGO, https://projectindigo.eu
Project-URL: LBI - ArchPro, https://archpro.lbg.ac.at
Project-URL: TU Wien - GEO Department, https://www.geo.tuwien.ac.at/
Classifier: Programming Language :: Python :: 3.8
Classifier: License :: OSI Approved :: GNU General Public License v3 (GPLv3)
Classifier: Operating System :: OS Independent
Requires-Python: >=3.8
License-File: LICENSE.txt
Requires-Dist: numpy (>=1.22)
Requires-Dist: opencv-python (>=4.6)
Requires-Dist: pandas (>=1.4)
Requires-Dist: PySide6 (>=6.3)
Requires-Dist: rawpy (>=0.17)
Requires-Dist: scipy (>=1.8)
Requires-Dist: seaborn (>=0.11)
Requires-Dist: matplotlib (>=3.1)
